spgci_ae/__init__.py
spgci_ae/hello.py
spgci_ae/pyarmor_runtime_000000/__init__.py
spgci_ae/pyarmor_runtime_000000/pyarmor_runtime.pyd
spgci_ae-0.0.37.dist-info/METADATA
spgci_ae-0.0.37.dist-info/WHEEL
spgci_ae-0.0.37.dist-info/top_level.txt
spgci_ae-0.0.37.dist-info/RECORD
